COPYING
MANIFEST.in
README.rst
buildout.cfg
requirements.txt
setup.py
version.txt
bob/__init__.py
bob.db.pericrosseye.egg-info/PKG-INFO
bob.db.pericrosseye.egg-info/SOURCES.txt
bob.db.pericrosseye.egg-info/dependency_links.txt
bob.db.pericrosseye.egg-info/entry_points.txt
bob.db.pericrosseye.egg-info/namespace_packages.txt
bob.db.pericrosseye.egg-info/not-zip-safe
bob.db.pericrosseye.egg-info/requires.txt
bob.db.pericrosseye.egg-info/top_level.txt
bob/db/__init__.py
bob/db/pericrosseye/__init__.py
bob/db/pericrosseye/create.py
bob/db/pericrosseye/driver.py
bob/db/pericrosseye/models.py
bob/db/pericrosseye/query.py
bob/db/pericrosseye/test.py
bob/db/pericrosseye/utils.py
doc/conf.py
doc/guide.rst
doc/index.rst
doc/py_api.rst